ai_assistant/__init__.py
ai_assistant/cli.py
ai_assistant/core/__init__.py
ai_assistant/core/app.py
ai_assistant/core/assistant.py
ai_assistant/core/conversation.py
ai_assistant/core/email_manager.py
ai_assistant/core/prompts.py
ai_assistant/integrations/__init__.py
ai_assistant/integrations/app_launcher.py
ai_assistant/integrations/email_manager.py
ai_assistant/integrations/file_explorer.py
ai_assistant/integrations/github.py
ai_assistant/integrations/whatsapp_manager.py
ai_assistant/utils/__init__.py
ai_assistant/utils/app_intent.py
ai_assistant/utils/email_intent.py
ai_assistant/utils/file_intent.py
ai_assistant/utils/github_intent.py
ai_assistant/utils/ocr.py
ai_assistant/utils/screenshot.py
ai_assistant/utils/speech.py
ai_assistant/utils/whatsapp_intent.py
quackquery-5.0.dist-info/licenses/LICENSE
quackquery-5.0.dist-info/METADATA
quackquery-5.0.dist-info/WHEEL
quackquery-5.0.dist-info/entry_points.txt
quackquery-5.0.dist-info/top_level.txt
quackquery-5.0.dist-info/RECORD
