Metadata-Version: 2.4
Name: QuackQuery
Version: 5.0
Summary: A versatile AI assistant with multi-model support
Home-page: https://github.com/kushagra2503/ai_assistant
Author: Kushagra
Author-email: radhikayash2@gmail.com
License: MIT
Project-URL: Bug Tracker, https://github.com/kushagra2503/ai_assistant/issues
Project-URL: Documentation, https://github.com/kushagra2503/ai_assistant#readme
Project-URL: Source Code, https://github.com/kushagra2503/ai_assistant
Classifier: Programming Language :: Python :: 3
Classifier: Programming Language :: Python :: 3.8
Classifier: Programming Language :: Python :: 3.9
Classifier: Programming Language :: Python :: 3.10
Classifier: License :: OSI Approved :: MIT License
Classifier: Operating System :: OS Independent
Classifier: Development Status :: 4 - Beta
Classifier: Intended Audience :: End Users/Desktop
Classifier: Topic :: Utilities
Requires-Python: >=3.7
License-File: LICENSE
Requires-Dist: google-generativeai
Requires-Dist: openai
Requires-Dist: SpeechRecognition
Requires-Dist: pillow
Requires-Dist: opencv-python
Requires-Dist: python-dotenv>=0.19.2
Requires-Dist: gtts
Requires-Dist: pytesseract
Requires-Dist: requests
Requires-Dist: send2trash
Requires-Dist: pywin32; platform_system == "Windows"
Requires-Dist: pyaudio
Requires-Dist: rich
Requires-Dist: email-validator>=2.0.0
Requires-Dist: selenium
Requires-Dist: webdriver-manager
Dynamic: author
Dynamic: author-email
Dynamic: classifier
Dynamic: description
Dynamic: description-content-type
Dynamic: home-page
Dynamic: license
Dynamic: license-file
Dynamic: project-url
Dynamic: requires-dist
Dynamic: requires-python
Dynamic: summary
